htmlwhat/Feedback.py
htmlwhat/Reporter.py
htmlwhat/State.py
htmlwhat/__init__.py
htmlwhat/failure.py
htmlwhat/sct_context.py
htmlwhat/sct_syntax.py
htmlwhat/test_exercise.py
htmlwhat/utils.py
htmlwhat/checks/__init__.py
htmlwhat/checks/check_doc.py
htmlwhat/checks/check_func.py
htmlwhat/checks/has_func.py
htmlwhat-1.0.2.dist-info/LICENSE
htmlwhat-1.0.2.dist-info/METADATA
htmlwhat-1.0.2.dist-info/WHEEL
htmlwhat-1.0.2.dist-info/top_level.txt
htmlwhat-1.0.2.dist-info/RECORD
