Metadata-Version: 2.1
Name: htmlwhat
Version: 1.0.2
Summary: Verify HTML code submissions and auto-generate meaningful feedback messages.
Home-page: https://github.com/arlarse/htmlwhat
Author: SHRAY SALVI
Author-email: shraysalvi@yahoo.com
License: UNKNOWN
Keywords: htmlwhat,html,feedback,html validation,testing,html testing
Platform: UNKNOWN
Classifier: License :: OSI Approved :: Apache Software License
Classifier: Intended Audience :: Developers
Classifier: Intended Audience :: Education
Classifier: Programming Language :: Python :: 3
Classifier: Operating System :: Unix
Classifier: Operating System :: MacOS :: MacOS X
Classifier: Operating System :: Microsoft :: Windows
Requires-Dist: beautifulsoup4 ~=4.12.3
Requires-Dist: protowhat ~=2.1.3
